Workbook

Sheet Data
A1: Date | B1: S&P 500 Pure Growth | C1: S&P 500 Pure Value | D1: BIL (1-3mo T-Bill / Cash) | E1: SPTL (Long Treasury) | F1: SPTI (Interm. Treasury) | G1: LQD (IG Corporate) | H1: PFF (Preferred) | I1: HYG (High Yield) | J1: MBB (Agency MBS) | K1: CMBS (CMBS) | M1: Source: Bloomberg Terminal, downloaded 6/18/2026 (BT HIST 10 YR Data). Monthly total-return levels, 5/31/2016-5/29/2026.
A2: 42521 | B2: 9483.3 | C2: 9162.45 | D2: 91.42 | E2: 38.671 | F2: 30.8375 | G2: 124.2161 | H2: 42.3537 | I2: 89.2754 | J2: 112.85 | K2: 53.7447
A3: 42551 | B3: 9407.22 | C3: 9054.78 | D3: 91.4 | E3: 41.186 | F3: 31.2951 | G3: 128.0544 | H3: 42.8547 | I3: 90.875 | J3: 113.6846 | K3: 54.7251
A4: 42580 | B4: 9870.98 | C4: 9455.05 | D4: 91.44 | E4: 42.015 | F4: 31.3249 | G4: 129.7123 | H4: 43.4526 | I4: 92.0672 | J4: 114.0354 | K4: 55.0997
A5: 42613 | B5: 9818.51 | C5: 9423.13 | D5: 91.44 | E5: 41.5789 | F5: 31.1474 | G5: 129.9478 | H5: 43.4632 | I5: 93.8813 | J5: 114.0179 | K5: 54.95
A6: 42643 | B6: 9806.85 | C6: 9442.54 | D6: 91.46 | E6: 41.0158 | F6: 31.2289 | G6: 129.5375 | H6: 42.9963 | I6: 94.8931 | J6: 114.3659 | K6: 54.9239
A7: 42674 | B7: 9560.7 | C7: 9349.54 | D7: 91.48 | E7: 39.2853 | F7: 31.0602 | G7: 127.558 | H7: 42.5786 | I7: 93.9603 | J7: 114.0517 | K7: 54.2052
A8: 42704 | B8: 9712.9 | C8: 10149.98 | D8: 91.44 | E8: 36.1788 | F8: 30.494 | G8: 123.5184 | H8: 41.161 | I8: 93.9792 | J8: 111.9063 | K8: 53.1093
A9: 42734 | B9: 9742.35 | C9: 10318.28 | D9: 91.4608 | E9: 36.0227 | F9: 30.4949 | G9: 124.5563 | H9: 41.2892 | I9: 95.7079 | J9: 111.7746 | K9: 53.2186
A10: 42766 | B10: 10027.04 | C10: 10448.25 | D10: 91.5008 | E10: 36.292 | F10: 30.5715 | G10: 124.737 | H10: 42.2768 | I10: 96.5815 | J10: 111.8797 | K10: 53.2915
A11: 42794 | B11: 10335.06 | C11: 10889.54 | D11: 91.546 | E11: 36.88 | F11: 30.6306 | G11: 126.385 | H11: 43.1595 | I11: 98.0595 | J11: 112.4094 | K11: 53.586
A12: 42825 | B12: 10489.33 | C12: 10621.35 | D12: 91.5303 | E12: 36.6219 | F12: 30.6643 | G12: 126.0138 | H12: 43.3742 | I12: 97.9174 | J12: 112.4231 | K12: 53.6109
A13: 42853 | B13: 10696.57 | C13: 10623.46 | D13: 91.5993 | E13: 37.2011 | F13: 30.8234 | G13: 127.5107 | H13: 43.9366 | I13: 98.7159 | J13: 113.1264 | K13: 53.9362
... A122: 46171 | B122: 38258.23 | C122: 25935.41 | D122: 113.393 | E122: 35.3906 | F122: 35.5042 | G122: 161.4708 | H122: 59.3584 | I122: 145.4491 | J122: 129.2604 | K122: 66.5022

Sheet Monthly Returns
A1: Month End | B1: S&P 500 Pure Growth | C1: S&P 500 Pure Value | D1: BIL (1-3mo T-Bill / Cash) | E1: SPTL (Long Treasury) | F1: SPTI (Interm. Treasury) | G1: LQD (IG Corporate) | H1: PFF (Preferred) | I1: HYG (High Yield) | J1: MBB (Agency MBS) | K1: CMBS (CMBS)
A2: =Data!A3 -> 42551 | B2: =Data!B3/Data!B2-1 -> -0.0080225238 | C2: =Data!C3/Data!C2-1 -> -0.011751224 | D2: =Data!D3/Data!D2-1 -> -0.00021877051 | E2: =Data!E3/Data!E2-1 -> 0.065035815 | F2: =Data!F3/Data!F2-1 -> 0.014839076 | G2: =Data!G3/Data!G2-1 -> 0.030900181 | H2: =Data!H3/Data!H2-1 -> 0.011828955 | I2: =Data!I3/Data!I2-1 -> 0.01791759 | ... K2: =Data!K3/Data!K2-1 -> 0.018241799
A3: =Data!A4 -> 42580 | B3: =Data!B4/Data!B3-1 -> 0.049298305 | C3: =Data!C4/Data!C3-1 -> 0.044205381 | D3: =Data!D4/Data!D3-1 -> 0.00043763676 | E3: =Data!E4/Data!E3-1 -> 0.020128199 | F3: =Data!F4/Data!F3-1 -> 0.00095222575 | G3: =Data!G4/Data!G3-1 -> 0.012946841 | H3: =Data!H4/Data!H3-1 -> 0.013951795 | I3: =Data!I4/Data!I3-1 -> 0.01311912 | ... K3: =Data!K4/Data!K3-1 -> 0.0068451223
A4: =Data!A5 -> 42613 | B4: =Data!B5/Data!B4-1 -> -0.0053155816 | C4: =Data!C5/Data!C4-1 -> -0.0033759737 | D4: =Data!D5/Data!D4-1 -> 0 | E4: =Data!E5/Data!E4-1 -> -0.010379626 | F4: =Data!F5/Data!F4-1 -> -0.0056664187 | G4: =Data!G5/Data!G4-1 -> 0.0018155564 | H4: =Data!H5/Data!H4-1 -> 0.00024394398 | I4: =Data!I5/Data!I4-1 -> 0.019704086 | ... K4: =Data!K5/Data!K4-1 -> -0.0027168932
A5: =Data!A6 -> 42643 | B5: =Data!B6/Data!B5-1 -> -0.0011875529 | C5: =Data!C6/Data!C5-1 -> 0.0020598251 | D5: =Data!D6/Data!D5-1 -> 0.00021872266 | E5: =Data!E6/Data!E5-1 -> -0.013542927 | F5: =Data!F6/Data!F5-1 -> 0.0026165908 | G5: =Data!G6/Data!G5-1 -> -0.0031574217 | H5: =Data!H6/Data!H5-1 -> -0.010742421 | I5: =Data!I6/Data!I5-1 -> 0.010777439 | ... K5: =Data!K6/Data!K5-1 -> -0.00047497725
A6: =Data!A7 -> 42674 | B6: =Data!B7/Data!B6-1 -> -0.025099803 | C6: =Data!C7/Data!C6-1 -> -0.0098490449 | D6: =Data!D7/Data!D6-1 -> 0.00021867483 | E6: =Data!E7/Data!E6-1 -> -0.042191058 | F6: =Data!F7/Data!F6-1 -> -0.0054020475 | G6: =Data!G7/Data!G6-1 -> -0.015281289 | H6: =Data!H7/Data!H6-1 -> -0.0097147894 | I6: =Data!I7/Data!I6-1 -> -0.0098300087 | ... K6: =Data!K7/Data!K6-1 -> -0.013085378
A7: =Data!A8 -> 42704 | B7: =Data!B8/Data!B7-1 -> 0.015919336 | C7: =Data!C8/Data!C7-1 -> 0.085612768 | D7: =Data!D8/Data!D7-1 -> -0.00043725404 | E7: =Data!E8/Data!E7-1 -> -0.079075379 | F7: =Data!F8/Data!F7-1 -> -0.018229116 | G7: =Data!G8/Data!G7-1 -> -0.031668731 | H7: =Data!H8/Data!H7-1 -> -0.03329372 | I7: =Data!I8/Data!I7-1 -> 0.00020114878 | ... K7: =Data!K8/Data!K7-1 -> -0.020217617
A8: =Data!A9 -> 42734 | B8: =Data!B9/Data!B8-1 -> 0.0030320502 | C8: =Data!C9/Data!C8-1 -> 0.016581313 | D8: =Data!D9/Data!D8-1 -> 0.00022747157 | E8: =Data!E9/Data!E8-1 -> -0.0043146815 | F8: =Data!F9/Data!F8-1 -> 2.9514003e-05 | G8: =Data!G9/Data!G8-1 -> 0.0084027967 | H8: =Data!H9/Data!H8-1 -> 0.0031145988 | I8: =Data!I9/Data!I8-1 -> 0.018394496 | ... K8: =Data!K9/Data!K8-1 -> 0.00205802
A9: =Data!A10 -> 42766 | B9: =Data!B10/Data!B9-1 -> 0.029221902 | C9: =Data!C10/Data!C9-1 -> 0.012596092 | D9: =Data!D10/Data!D9-1 -> 0.00043734584 | E9: =Data!E10/Data!E9-1 -> 0.0074758416 | F9: =Data!F10/Data!F9-1 -> 0.0025118954 | G9: =Data!G10/Data!G9-1 -> 0.0014507496 | H9: =Data!H10/Data!H9-1 -> 0.023919088 | I9: =Data!I10/Data!I9-1 -> 0.0091277732 | ... K9: =Data!K10/Data!K9-1 -> 0.0013698218
A10: =Data!A11 -> 42794 | B10: =Data!B11/Data!B10-1 -> 0.030718936 | C10: =Data!C11/Data!C10-1 -> 0.042235781 | D10: =Data!D11/Data!D10-1 -> 0.00049398475 | E10: =Data!E11/Data!E10-1 -> 0.016201918 | F10: =Data!F11/Data!F10-1 -> 0.0019331731 | G10: =Data!G11/Data!G10-1 -> 0.013211798 | H10: =Data!H11/Data!H10-1 -> 0.020879064 | I10: =Data!I11/Data!I10-1 -> 0.015303138 | ... K10: =Data!K11/Data!K10-1 -> 0.0055262096
A11: =Data!A12 -> 42825 | B11: =Data!B12/Data!B11-1 -> 0.014926861 | C11: =Data!C12/Data!C11-1 -> -0.024628221 | D11: =Data!D12/Data!D11-1 -> -0.00017149848 | E11: =Data!E12/Data!E11-1 -> -0.0069983731 | F11: =Data!F12/Data!F11-1 -> 0.001100207 | G11: =Data!G12/Data!G11-1 -> -0.0029370574 | H11: =Data!H12/Data!H11-1 -> 0.0049745711 | I11: =Data!I12/Data!I11-1 -> -0.0014491202 | ... K11: =Data!K12/Data!K11-1 -> 0.00046467361
A12: =Data!A13 -> 42853 | B12: =Data!B13/Data!B12-1 -> 0.01975722 | C12: =Data!C13/Data!C12-1 -> 0.00019865648 | D12: =Data!D13/Data!D12-1 -> 0.00075384873 | E12: =Data!E13/Data!E12-1 -> 0.015815673 | F12: =Data!F13/Data!F12-1 -> 0.0051884439 | G12: =Data!G13/Data!G12-1 -> 0.011878858 | H12: =Data!H13/Data!H12-1 -> 0.012966233 | I12: =Data!I13/Data!I12-1 -> 0.0081548325 | ... K12: =Data!K13/Data!K12-1 -> 0.0060677959
A13: =Data!A14 -> 42886 | B13: =Data!B14/Data!B13-1 -> 0.031822351 | C13: =Data!C14/Data!C13-1 -> -0.010350677 | D13: =Data!D14/Data!D13-1 -> 0.00014519762 | E13: =Data!E14/Data!E13-1 -> 0.01801022 | F13: =Data!F14/Data!F13-1 -> 0.0039353219 | G13: =Data!G14/Data!G13-1 -> 0.013336136 | H13: =Data!H14/Data!H13-1 -> 0.0055398005 | I13: =Data!I14/Data!I13-1 -> 0.010305331 | ... K13: =Data!K14/Data!K13-1 -> 0.0080261494
... A121: =Data!A122 -> 46171 | B121: =Data!B122/Data!B121-1 -> 0.10622188 | C121: =Data!C122/Data!C121-1 -> 0.017970317 | D121: =Data!D122/Data!D121-1 -> 0.0031724855 | E121: =Data!E122/Data!E121-1 -> 0.004624202 | F121: =Data!F122/Data!F121-1 -> -0.00069520869 | G121: =Data!G122/Data!G121-1 -> 0.0086131778 | H121: =Data!H122/Data!H121-1 -> 0.0079811983 | I121: =Data!I122/Data!I121-1 -> 0.004354416 | ... K121: =Data!K122/Data!K121-1 -> 0.0014682696

Sheet Summary Stats
A1: 10-Year Risk & Return Summary (June 2016 - May 2026, monthly data, N = 120)
A2: Sharpe ratio uses BIL (cash) as the risk-free return.
A4: Metric | B4: S&P 500 Pure Growth | C4: S&P 500 Pure Value | D4: BIL (1-3mo T-Bill / Cash) | E4: SPTL (Long Treasury) | F4: SPTI (Interm. Treasury) | G4: LQD (IG Corporate) | H4: PFF (Preferred) | I4: HYG (High Yield) | J4: MBB (Agency MBS) | K4: CMBS (CMBS)
A5: Avg Monthly Return | B5: =AVERAGE('Monthly Returns'!B$2:B$121) -> 0.013236192 | C5: =AVERAGE('Monthly Returns'!C$2:C$121) -> 0.010552213 | D5: =AVERAGE('Monthly Returns'!D$2:D$121) -> 0.0017978853 | E5: =AVERAGE('Monthly Returns'!E$2:E$121) -> -4.2819944e-05 | F5: =AVERAGE('Monthly Returns'!F$2:F$121) -> 0.0012560705 | G5: =AVERAGE('Monthly Returns'!G$2:G$121) -> 0.0024709367 | H5: =AVERAGE('Monthly Returns'!H$2:H$121) -> 0.0032400355 | I5: =AVERAGE('Monthly Returns'!I$2:I$121) -> 0.0043002871 | ... K5: =AVERAGE('Monthly Returns'!K$2:K$121) -> 0.0018559207
A6: Monthly Std Dev | B6: =STDEV('Monthly Returns'!B$2:B$121) -> 0.05574417 | C6: =STDEV('Monthly Returns'!C$2:C$121) -> 0.059824162 | D6: =STDEV('Monthly Returns'!D$2:D$121) -> 0.0016283214 | E6: =STDEV('Monthly Returns'!E$2:E$121) -> 0.037550363 | F6: =STDEV('Monthly Returns'!F$2:F$121) -> 0.012789152 | G6: =STDEV('Monthly Returns'!G$2:G$121) -> 0.023879156 | H6: =STDEV('Monthly Returns'!H$2:H$121) -> 0.029196363 | I6: =STDEV('Monthly Returns'!I$2:I$121) -> 0.021152447 | ... K6: =STDEV('Monthly Returns'!K$2:K$121) -> 0.012657863
A7: Annualized Return (CAGR) | B7: =(Data!B$122/Data!B$2)^(1/10)-1 -> 0.14967884 | C7: =(Data!C$122/Data!C$2)^(1/10)-1 -> 0.10965545 | D7: =(Data!D$122/Data!D$2)^(1/10)-1 -> 0.021773189 | E7: =(Data!E$122/Data!E$2)^(1/10)-1 -> -0.008825199 | F7: =(Data!F$122/Data!F$2)^(1/10)-1 -> 0.014191711 | G7: =(Data!G$122/Data!G$2)^(1/10)-1 -> 0.026577191 | H7: =(Data!H$122/Data!H$2)^(1/10)-1 -> 0.034329909 | I7: =(Data!I$122/Data!I$2)^(1/10)-1 -> 0.050020851 | ... K7: =(Data!K$122/Data!K$2)^(1/10)-1 -> 0.02152744
A8: Annualized Std Dev | B8: =B6*SQRT(12) -> 0.19310347 | C8: =C6*SQRT(12) -> 0.20723698 | D8: =D6*SQRT(12) -> 0.0056406708 | E8: =E6*SQRT(12) -> 0.13007827 | F8: =F6*SQRT(12) -> 0.044302923 | G8: =G6*SQRT(12) -> 0.082719823 | H8: =H6*SQRT(12) -> 0.10113917 | I8: =I6*SQRT(12) -> 0.073274227 | ... K8: =K6*SQRT(12) -> 0.043848123
A9: Growth of $1 (10 yrs) | B9: =Data!B$122/Data!B$2 -> 4.0342739 | C9: =Data!C$122/Data!C$2 -> 2.8306195 | D9: =Data!D$122/Data!D$2 -> 1.2403522 | E9: =Data!E$122/Data!E$2 -> 0.91517158 | F9: =Data!F$122/Data!F$2 -> 1.151332 | G9: =Data!G$122/Data!G$2 -> 1.2999184 | H9: =Data!H$122/Data!H$2 -> 1.4014927 | I9: =Data!I$122/Data!I$2 -> 1.6292181 | ... K9: =Data!K$122/Data!K$2 -> 1.2373722
A10: Sharpe Ratio (vs. BIL) | B10: =(B7-$D$7)/B8 -> 0.66236848 | C10: =(C7-$D$7)/C8 -> 0.4240665 | D10: n.a. | E10: =(E7-$D$7)/E8 -> -0.23523058 | F10: =(F7-$D$7)/F8 -> -0.17112817 | G10: =(G7-$D$7)/G8 -> 0.058075583 | H10: =(H7-$D$7)/H8 -> 0.12415288 | I10: =(I7-$D$7)/I8 -> 0.38550611 | J10: =(J7-$D$7)/J8 -> -0.15691144 | K10: =(K7-$D$7)/K8 -> -0.0056045587
A11: Best Month | B11: =MAX('Monthly Returns'!B$2:B$121) -> 0.16564759 | C11: =MAX('Monthly Returns'!C$2:C$121) -> 0.18898825 | D11: =MAX('Monthly Returns'!D$2:D$121) -> 0.0049622444 | E11: =MAX('Monthly Returns'!E$2:E$121) -> 0.10826533 | F11: =MAX('Monthly Returns'!F$2:F$121) -> 0.031010817 | G11: =MAX('Monthly Returns'!G$2:G$121) -> 0.075692917 | H11: =MAX('Monthly Returns'!H$2:H$121) -> 0.10055594 | I11: =MAX('Monthly Returns'!I$2:I$121) -> 0.066946561 | ... K11: =MAX('Monthly Returns'!K$2:K$121) -> 0.031203194
A12: Worst Month | B12: =MIN('Monthly Returns'!B$2:B$121) -> -0.15562486 | C12: =MIN('Monthly Returns'!C$2:C$121) -> -0.28736172 | D12: =MIN('Monthly Returns'!D$2:D$121) -> -0.00043725404 | E12: =MIN('Monthly Returns'!E$2:E$121) -> -0.090727419 | F12: =MIN('Monthly Returns'!F$2:F$121) -> -0.033491597 | G12: =MIN('Monthly Returns'!G$2:G$121) -> -0.067000454 | H12: =MIN('Monthly Returns'!H$2:H$121) -> -0.1190316 | I12: =MIN('Monthly Returns'!I$2:I$121) -> -0.10031097 | ... K12: =MIN('Monthly Returns'!K$2:K$121) -> -0.03168904
A13: 2022 Rate-Shock Return | B13: =Data!B81/Data!B69-1 -> -0.27271786 | C13: =Data!C81/Data!C69-1 -> -0.0084158629 | D13: =Data!D81/Data!D69-1 -> 0.013798282 | E13: =Data!E81/Data!E69-1 -> -0.29448165 | F13: =Data!F81/Data!F69-1 -> -0.10648717 | G13: =Data!G81/Data!G69-1 -> -0.17933679 | H13: =Data!H81/Data!H69-1 -> -0.18184145 | I13: =Data!I81/Data!I69-1 -> -0.10993149 | ... K13: =Data!K81/Data!K69-1 -> -0.11209463

Sheet Calendar Year Returns
A1: Calendar-Year Total Returns
A3: Year | B3: S&P 500 Pure Growth | C3: S&P 500 Pure Value | D3: BIL (1-3mo T-Bill / Cash) | E3: SPTL (Long Treasury) | F3: SPTI (Interm. Treasury) | G3: LQD (IG Corporate) | H3: PFF (Preferred) | I3: HYG (High Yield) | J3: MBB (Agency MBS) | K3: CMBS (CMBS)
A4: 2016 (Jun-Dec) | B4: =Data!B9/Data!B2-1 -> 0.02731644 | C4: =Data!C9/Data!C2-1 -> 0.12614857 | D4: =Data!D9/Data!D2-1 -> 0.00044629184 | E4: =Data!E9/Data!E2-1 -> -0.068482842 | F4: =Data!F9/Data!F2-1 -> -0.01110985 | G4: =Data!G9/Data!G2-1 -> 0.0027387754 | H4: =Data!H9/Data!H2-1 -> -0.025133577 | I4: =Data!I9/Data!I2-1 -> 0.072052323 | ... K4: =Data!K9/Data!K2-1 -> -0.0097888722
A5: 2017 | B5: =Data!B21/Data!B9-1 -> 0.26757918 | C5: =Data!C21/Data!C9-1 -> 0.17726598 | D5: =Data!D21/Data!D9-1 -> 0.0068630495 | E5: =Data!E21/Data!E9-1 -> 0.090193128 | F5: =Data!F21/Data!F9-1 -> 0.010372226 | G5: =Data!G21/Data!G9-1 -> 0.07055444 | H5: =Data!H21/Data!H9-1 -> 0.080989702 | I5: =Data!I21/Data!I9-1 -> 0.060682556 | ... K5: =Data!K21/Data!K9-1 -> 0.029482174
A6: 2018 | B6: =Data!B33/Data!B21-1 -> -0.042156577 | C6: =Data!C33/Data!C21-1 -> -0.11997751 | D6: =Data!D33/Data!D21-1 -> 0.017391965 | E6: =Data!E33/Data!E21-1 -> -0.015642307 | F6: =Data!F33/Data!F21-1 -> 0.022680064 | G6: =Data!G33/Data!G21-1 -> -0.037856886 | H6: =Data!H33/Data!H21-1 -> -0.04627273 | I6: =Data!I33/Data!I21-1 -> -0.020240219 | ... K6: =Data!K33/Data!K21-1 -> 0.007735327
A7: 2019 | B7: =Data!B45/Data!B33-1 -> 0.28986271 | C7: =Data!C45/Data!C33-1 -> 0.25453159 | D7: =Data!D45/Data!D33-1 -> 0.020314846 | E7: =Data!E45/Data!E33-1 -> 0.1374407 | F7: =Data!F45/Data!F33-1 -> 0.060149159 | G7: =Data!G45/Data!G33-1 -> 0.17366128 | H7: =Data!H45/Data!H33-1 -> 0.15929139 | I7: =Data!I45/Data!I33-1 -> 0.14088839 | ... K7: =Data!K45/Data!K33-1 -> 0.079302463
A8: 2020 | B8: =Data!B57/Data!B45-1 -> 0.29659434 | C8: =Data!C57/Data!C45-1 -> -0.087148643 | D8: =Data!D57/Data!D45-1 -> 0.0040013223 | E8: =Data!E57/Data!E45-1 -> 0.18069842 | F8: =Data!F57/Data!F45-1 -> 0.077008738 | G8: =Data!G57/Data!G45-1 -> 0.10972901 | H8: =Data!H57/Data!H45-1 -> 0.079098495 | I8: =Data!I57/Data!I45-1 -> 0.04476536 | ... K8: =Data!K57/Data!K45-1 -> 0.078615803
A9: 2021 | B9: =Data!B69/Data!B57-1 -> 0.29809089 | C9: =Data!C69/Data!C57-1 -> 0.34633079 | D9: =Data!D69/Data!D57-1 -> -0.00098358025 | E9: =Data!E69/Data!E57-1 -> -0.049984687 | F9: =Data!F69/Data!F57-1 -> -0.025468483 | G9: =Data!G69/Data!G57-1 -> -0.018443557 | H9: =Data!H69/Data!H57-1 -> 0.071356944 | I9: =Data!I69/Data!I57-1 -> 0.037476719 | ... K9: =Data!K69/Data!K57-1 -> -0.018172059
A10: 2022 | B10: =Data!B81/Data!B69-1 -> -0.27271786 | C10: =Data!C81/Data!C69-1 -> -0.0084158629 | D10: =Data!D81/Data!D69-1 -> 0.013798282 | E10: =Data!E81/Data!E69-1 -> -0.29448165 | F10: =Data!F81/Data!F69-1 -> -0.10648717 | G10: =Data!G81/Data!G69-1 -> -0.17933679 | H10: =Data!H81/Data!H69-1 -> -0.18184145 | I10: =Data!I81/Data!I69-1 -> -0.10993149 | ... K10: =Data!K81/Data!K69-1 -> -0.11209463
A11: 2023 | B11: =Data!B93/Data!B81-1 -> 0.083067666 | C11: =Data!C93/Data!C81-1 -> 0.082306712 | D11: =Data!D93/Data!D81-1 -> 0.049437012 | E11: =Data!E93/Data!E81-1 -> 0.033103619 | F11: =Data!F93/Data!F81-1 -> 0.042419058 | G11: =Data!G93/Data!G81-1 -> 0.09403742 | H11: =Data!H93/Data!H81-1 -> 0.091958652 | I11: =Data!I93/Data!I81-1 -> 0.11528343 | ... K11: =Data!K93/Data!K81-1 -> 0.050550929
A12: 2024 | B12: =Data!B105/Data!B93-1 -> 0.28862134 | C12: =Data!C105/Data!C93-1 -> 0.12778134 | D12: =Data!D105/Data!D93-1 -> 0.051909617 | E12: =Data!E105/Data!E93-1 -> -0.062358305 | F12: =Data!F105/Data!F93-1 -> 0.013142745 | G12: =Data!G105/Data!G93-1 -> 0.0085746008 | H12: =Data!H105/Data!H93-1 -> 0.072397631 | I12: =Data!I105/Data!I93-1 -> 0.079678221 | ... K12: =Data!K105/Data!K93-1 -> 0.042711216
A13: 2025 | B13: =Data!B117/Data!B105-1 -> 0.13754996 | C13: =Data!C117/Data!C105-1 -> 0.17728801 | D13: =Data!D117/Data!D105-1 -> 0.04148071 | E13: =Data!E117/Data!E105-1 -> 0.052822856 | F13: =Data!F117/Data!F105-1 -> 0.074590461 | G13: =Data!G117/Data!G105-1 -> 0.078960055 | H13: =Data!H117/Data!H105-1 -> 0.048686425 | I13: =Data!I117/Data!I105-1 -> 0.085971879 | ... K13: =Data!K117/Data!K105-1 -> 0.076687092
A14: 2026 YTD (May) | B14: =Data!B122/Data!B117-1 -> 0.2902816 | C14: =Data!C122/Data!C117-1 -> 0.10432385 | D14: =Data!D122/Data!D117-1 -> 0.014644351 | E14: =Data!E122/Data!E117-1 -> -0.0027305389 | F14: =Data!F122/Data!F117-1 -> -0.0013978776 | G14: =Data!G122/Data!G117-1 -> 0.0076143241 | H14: =Data!H122/Data!H117-1 -> 0.035540079 | I14: =Data!I122/Data!I117-1 -> 0.016006125 | ... K14: =Data!K122/Data!K117-1 -> 0.0062932862

Sheet Correlations
A1: Correlation Matrix of Monthly Returns (10 yrs)
B3: S&P 500 Pure Growth | C3: S&P 500 Pure Value | D3: BIL (1-3mo T-Bill / Cash) | E3: SPTL (Long Treasury) | F3: SPTI (Interm. Treasury) | G3: LQD (IG Corporate) | H3: PFF (Preferred) | I3: HYG (High Yield) | J3: MBB (Agency MBS) | K3: CMBS (CMBS)
A4: S&P 500 Pure Growth | B4: =CORREL('Monthly Returns'!B$2:B$121,'Monthly Returns'!B$2:B$121) -> 1 | C4: =CORREL('Monthly Returns'!B$2:B$121,'Monthly Returns'!C$2:C$121) -> 0.68682836 | D4: =CORREL('Monthly Returns'!B$2:B$121,'Monthly Returns'!D$2:D$121) -> -0.022126331 | E4: =CORREL('Monthly Returns'!B$2:B$121,'Monthly Returns'!E$2:E$121) -> 0.19197807 | F4: =CORREL('Monthly Returns'!B$2:B$121,'Monthly Returns'!F$2:F$121) -> 0.15696975 | G4: =CORREL('Monthly Returns'!B$2:B$121,'Monthly Returns'!G$2:G$121) -> 0.57250023 | H4: =CORREL('Monthly Returns'!B$2:B$121,'Monthly Returns'!H$2:H$121) -> 0.72542433 | I4: =CORREL('Monthly Returns'!B$2:B$121,'Monthly Returns'!I$2:I$121) -> 0.74779886 | J4: =CORREL('Monthly Returns'!B$2:B$121,'Monthly Returns'!J$2:J$121) -> 0.34375769 | K4: =CORREL('Monthly Returns'!B$2:B$121,'Monthly Returns'!K$2:K$121) -> 0.34848227
A5: S&P 500 Pure Value | B5: =CORREL('Monthly Returns'!C$2:C$121,'Monthly Returns'!B$2:B$121) -> 0.68682836 | C5: =CORREL('Monthly Returns'!C$2:C$121,'Monthly Returns'!C$2:C$121) -> 1 | D5: =CORREL('Monthly Returns'!C$2:C$121,'Monthly Returns'!D$2:D$121) -> -0.09694399 | E5: =CORREL('Monthly Returns'!C$2:C$121,'Monthly Returns'!E$2:E$121) -> -0.055017701 | F5: =CORREL('Monthly Returns'!C$2:C$121,'Monthly Returns'!F$2:F$121) -> -0.0449176 | G5: =CORREL('Monthly Returns'!C$2:C$121,'Monthly Returns'!G$2:G$121) -> 0.45225049 | H5: =CORREL('Monthly Returns'!C$2:C$121,'Monthly Returns'!H$2:H$121) -> 0.67036089 | I5: =CORREL('Monthly Returns'!C$2:C$121,'Monthly Returns'!I$2:I$121) -> 0.73864944 | J5: =CORREL('Monthly Returns'!C$2:C$121,'Monthly Returns'!J$2:J$121) -> 0.24886164 | K5: =CORREL('Monthly Returns'!C$2:C$121,'Monthly Returns'!K$2:K$121) -> 0.1631052
A6: BIL (1-3mo T-Bill / Cash) | B6: =CORREL('Monthly Returns'!D$2:D$121,'Monthly Returns'!B$2:B$121) -> -0.022126331 | C6: =CORREL('Monthly Returns'!D$2:D$121,'Monthly Returns'!C$2:C$121) -> -0.09694399 | D6: =CORREL('Monthly Returns'!D$2:D$121,'Monthly Returns'!D$2:D$121) -> 1 | E6: =CORREL('Monthly Returns'!D$2:D$121,'Monthly Returns'!E$2:E$121) -> 0.086896232 | F6: =CORREL('Monthly Returns'!D$2:D$121,'Monthly Returns'!F$2:F$121) -> 0.1683167 | G6: =CORREL('Monthly Returns'!D$2:D$121,'Monthly Returns'!G$2:G$121) -> 0.07493635 | H6: =CORREL('Monthly Returns'!D$2:D$121,'Monthly Returns'!H$2:H$121) -> 0.005355488 | I6: =CORREL('Monthly Returns'!D$2:D$121,'Monthly Returns'!I$2:I$121) -> 0.025011437 | J6: =CORREL('Monthly Returns'!D$2:D$121,'Monthly Returns'!J$2:J$121) -> 0.15350439 | K6: =CORREL('Monthly Returns'!D$2:D$121,'Monthly Returns'!K$2:K$121) -> 0.16444598
A7: SPTL (Long Treasury) | B7: =CORREL('Monthly Returns'!E$2:E$121,'Monthly Returns'!B$2:B$121) -> 0.19197807 | C7: =CORREL('Monthly Returns'!E$2:E$121,'Monthly Returns'!C$2:C$121) -> -0.055017701 | D7: =CORREL('Monthly Returns'!E$2:E$121,'Monthly Returns'!D$2:D$121) -> 0.086896232 | E7: =CORREL('Monthly Returns'!E$2:E$121,'Monthly Returns'!E$2:E$121) -> 1 | F7: =CORREL('Monthly Returns'!E$2:E$121,'Monthly Returns'!F$2:F$121) -> 0.87931709 | G7: =CORREL('Monthly Returns'!E$2:E$121,'Monthly Returns'!G$2:G$121) -> 0.76292633 | H7: =CORREL('Monthly Returns'!E$2:E$121,'Monthly Returns'!H$2:H$121) -> 0.37135679 | I7: =CORREL('Monthly Returns'!E$2:E$121,'Monthly Returns'!I$2:I$121) -> 0.28702848 | J7: =CORREL('Monthly Returns'!E$2:E$121,'Monthly Returns'!J$2:J$121) -> 0.80944194 | K7: =CORREL('Monthly Returns'!E$2:E$121,'Monthly Returns'!K$2:K$121) -> 0.80985922
A8: SPTI (Interm. Treasury) | B8: =CORREL('Monthly Returns'!F$2:F$121,'Monthly Returns'!B$2:B$121) -> 0.15696975 | C8: =CORREL('Monthly Returns'!F$2:F$121,'Monthly Returns'!C$2:C$121) -> -0.0449176 | D8: =CORREL('Monthly Returns'!F$2:F$121,'Monthly Returns'!D$2:D$121) -> 0.1683167 | E8: =CORREL('Monthly Returns'!F$2:F$121,'Monthly Returns'!E$2:E$121) -> 0.87931709 | F8: =CORREL('Monthly Returns'!F$2:F$121,'Monthly Returns'!F$2:F$121) -> 1 | G8: =CORREL('Monthly Returns'!F$2:F$121,'Monthly Returns'!G$2:G$121) -> 0.74275444 | H8: =CORREL('Monthly Returns'!F$2:F$121,'Monthly Returns'!H$2:H$121) -> 0.32102002 | I8: =CORREL('Monthly Returns'!F$2:F$121,'Monthly Returns'!I$2:I$121) -> 0.33273766 | J8: =CORREL('Monthly Returns'!F$2:F$121,'Monthly Returns'!J$2:J$121) -> 0.90048989 | K8: =CORREL('Monthly Returns'!F$2:F$121,'Monthly Returns'!K$2:K$121) -> 0.86567925
A9: LQD (IG Corporate) | B9: =CORREL('Monthly Returns'!G$2:G$121,'Monthly Returns'!B$2:B$121) -> 0.57250023 | C9: =CORREL('Monthly Returns'!G$2:G$121,'Monthly Returns'!C$2:C$121) -> 0.45225049 | D9: =CORREL('Monthly Returns'!G$2:G$121,'Monthly Returns'!D$2:D$121) -> 0.07493635 | E9: =CORREL('Monthly Returns'!G$2:G$121,'Monthly Returns'!E$2:E$121) -> 0.76292633 | F9: =CORREL('Monthly Returns'!G$2:G$121,'Monthly Returns'!F$2:F$121) -> 0.74275444 | G9: =CORREL('Monthly Returns'!G$2:G$121,'Monthly Returns'!G$2:G$121) -> 1 | H9: =CORREL('Monthly Returns'!G$2:G$121,'Monthly Returns'!H$2:H$121) -> 0.74398486 | I9: =CORREL('Monthly Returns'!G$2:G$121,'Monthly Returns'!I$2:I$121) -> 0.78057599 | J9: =CORREL('Monthly Returns'!G$2:G$121,'Monthly Returns'!J$2:J$121) -> 0.8419859 | K9: =CORREL('Monthly Returns'!G$2:G$121,'Monthly Returns'!K$2:K$121) -> 0.82953078
A10: PFF (Preferred) | B10: =CORREL('Monthly Returns'!H$2:H$121,'Monthly Returns'!B$2:B$121) -> 0.72542433 | C10: =CORREL('Monthly Returns'!H$2:H$121,'Monthly Returns'!C$2:C$121) -> 0.67036089 | D10: =CORREL('Monthly Returns'!H$2:H$121,'Monthly Returns'!D$2:D$121) -> 0.005355488 | E10: =CORREL('Monthly Returns'!H$2:H$121,'Monthly Returns'!E$2:E$121) -> 0.37135679 | F10: =CORREL('Monthly Returns'!H$2:H$121,'Monthly Returns'!F$2:F$121) -> 0.32102002 | G10: =CORREL('Monthly Returns'!H$2:H$121,'Monthly Returns'!G$2:G$121) -> 0.74398486 | H10: =CORREL('Monthly Returns'!H$2:H$121,'Monthly Returns'!H$2:H$121) -> 1 | I10: =CORREL('Monthly Returns'!H$2:H$121,'Monthly Returns'!I$2:I$121) -> 0.81409348 | J10: =CORREL('Monthly Returns'!H$2:H$121,'Monthly Returns'!J$2:J$121) -> 0.54826355 | K10: =CORREL('Monthly Returns'!H$2:H$121,'Monthly Returns'!K$2:K$121) -> 0.56397465
A11: HYG (High Yield) | B11: =CORREL('Monthly Returns'!I$2:I$121,'Monthly Returns'!B$2:B$121) -> 0.74779886 | C11: =CORREL('Monthly Returns'!I$2:I$121,'Monthly Returns'!C$2:C$121) -> 0.73864944 | D11: =CORREL('Monthly Returns'!I$2:I$121,'Monthly Returns'!D$2:D$121) -> 0.025011437 | E11: =CORREL('Monthly Returns'!I$2:I$121,'Monthly Returns'!E$2:E$121) -> 0.28702848 | F11: =CORREL('Monthly Returns'!I$2:I$121,'Monthly Returns'!F$2:F$121) -> 0.33273766 | G11: =CORREL('Monthly Returns'!I$2:I$121,'Monthly Returns'!G$2:G$121) -> 0.78057599 | H11: =CORREL('Monthly Returns'!I$2:I$121,'Monthly Returns'!H$2:H$121) -> 0.81409348 | I11: =CORREL('Monthly Returns'!I$2:I$121,'Monthly Returns'!I$2:I$121) -> 1 | J11: =CORREL('Monthly Returns'!I$2:I$121,'Monthly Returns'!J$2:J$121) -> 0.54097778 | K11: =CORREL('Monthly Returns'!I$2:I$121,'Monthly Returns'!K$2:K$121) -> 0.51309025
A12: MBB (Agency MBS) | B12: =CORREL('Monthly Returns'!J$2:J$121,'Monthly Returns'!B$2:B$121) -> 0.34375769 | C12: =CORREL('Monthly Returns'!J$2:J$121,'Monthly Returns'!C$2:C$121) -> 0.24886164 | D12: =CORREL('Monthly Returns'!J$2:J$121,'Monthly Returns'!D$2:D$121) -> 0.15350439 | E12: =CORREL('Monthly Returns'!J$2:J$121,'Monthly Returns'!E$2:E$121) -> 0.80944194 | F12: =CORREL('Monthly Returns'!J$2:J$121,'Monthly Returns'!F$2:F$121) -> 0.90048989 | G12: =CORREL('Monthly Returns'!J$2:J$121,'Monthly Returns'!G$2:G$121) -> 0.8419859 | H12: =CORREL('Monthly Returns'!J$2:J$121,'Monthly Returns'!H$2:H$121) -> 0.54826355 | I12: =CORREL('Monthly Returns'!J$2:J$121,'Monthly Returns'!I$2:I$121) -> 0.54097778 | J12: =CORREL('Monthly Returns'!J$2:J$121,'Monthly Returns'!J$2:J$121) -> 1 | K12: =CORREL('Monthly Returns'!J$2:J$121,'Monthly Returns'!K$2:K$121) -> 0.85236208
A13: CMBS (CMBS) | B13: =CORREL('Monthly Returns'!K$2:K$121,'Monthly Returns'!B$2:B$121) -> 0.34848227 | C13: =CORREL('Monthly Returns'!K$2:K$121,'Monthly Returns'!C$2:C$121) -> 0.1631052 | D13: =CORREL('Monthly Returns'!K$2:K$121,'Monthly Returns'!D$2:D$121) -> 0.16444598 | E13: =CORREL('Monthly Returns'!K$2:K$121,'Monthly Returns'!E$2:E$121) -> 0.80985922 | F13: =CORREL('Monthly Returns'!K$2:K$121,'Monthly Returns'!F$2:F$121) -> 0.86567925 | G13: =CORREL('Monthly Returns'!K$2:K$121,'Monthly Returns'!G$2:G$121) -> 0.82953078 | H13: =CORREL('Monthly Returns'!K$2:K$121,'Monthly Returns'!H$2:H$121) -> 0.56397465 | I13: =CORREL('Monthly Returns'!K$2:K$121,'Monthly Returns'!I$2:I$121) -> 0.51309025 | J13: =CORREL('Monthly Returns'!K$2:K$121,'Monthly Returns'!J$2:J$121) -> 0.85236208 | K13: =CORREL('Monthly Returns'!K$2:K$121,'Monthly Returns'!K$2:K$121) -> 1

Sheet Growth vs Value
A1: Equity Style Decision: S&P 500 Pure Growth vs. Pure Value (10 yrs)
A3: Metric | B3: Pure Growth | C3: Pure Value | D3: Growth minus Value
A4: Annualized Return (CAGR) | B4: ='Summary Stats'!B7 -> 0.14967884 | C4: ='Summary Stats'!C7 -> 0.10965545 | D4: =B4-C4 -> 0.040023392
A5: Annualized Std Dev | B5: ='Summary Stats'!B8 -> 0.19310347 | C5: ='Summary Stats'!C8 -> 0.20723698 | D5: =B5-C5 -> -0.014133508
A6: Sharpe Ratio (vs. BIL) | B6: ='Summary Stats'!B10 -> 0.66236848 | C6: ='Summary Stats'!C10 -> 0.4240665 | D6: =B6-C6 -> 0.23830198
A7: Growth of $1 | B7: ='Summary Stats'!B9 -> 4.0342739 | C7: ='Summary Stats'!C9 -> 2.8306195 | D7: =B7-C7 -> 1.2036544
A8: Worst Month | B8: ='Summary Stats'!B12 -> -0.15562486 | C8: ='Summary Stats'!C12 -> -0.28736172 | D8: =B8-C8 -> 0.13173686
A9: 2022 Rate-Shock Return | B9: ='Summary Stats'!B13 -> -0.27271786 | C9: ='Summary Stats'!C13 -> -0.0084158629 | D9: =B9-C9 -> -0.26430199
A10: 2026 YTD (through May) | B10: ='Calendar Year Returns'!B14 -> 0.2902816 | C10: ='Calendar Year Returns'!C14 -> 0.10432385 | D10: =B10-C10 -> 0.18595775

Sheet Current Fund Stats (Fwd)
A1: Forward-Looking Fund Statistics (issuer factsheet data, June–July 2026)
A2: Sources: ssga.com and ishares.com fund pages. Dates vary by fund (shown in last column). n.a. = not published for that fund.
A4: Fund | B4: 30-Day SEC Yield | C4: Yield to Maturity | D4: Effective Duration (yrs) | E4: Wtd Avg Maturity (yrs) | F4: Expense Ratio | G4: AUM ($B) | H4: Yield per Yr of Duration | I4: Data as of
A5: BIL (1-3mo T-Bill / Cash) | B5: 0.0351 | C5: 0.0368 | D5: 0.14 | E5: 0.15 | F5: 0.001353 | G5: 46.6 | H5: n.a. | I5: 7/2/2026
A6: SPTL (Long Treasury) | B6: 0.05 | C6: 0.0498 | D6: 14.2 | E6: 21.8 | F6: 0.0003 | G6: 10.6 | H6: =C6/D6 -> 0.0035070423 | I6: 7/2/2026
A7: SPTI (Interm. Treasury) | B7: 0.043 | C7: 0.0428 | D7: 4.9 | E7: 5.59 | F7: 0.0003 | G7: 10.3 | H7: =C7/D7 -> 0.0087346939 | I7: 7/2/2026
A8: LQD (IG Corporate) | B8: 0.0522 | C8: 0.0528 | D8: 7.99 | E8: 12.95 | F8: 0.0014 | G8: 32.1 | H8: =C8/D8 -> 0.0066082603 | I8: 6/25/2026
A9: PFF (Preferred) | B9: 0.0628 | C9: n.a. | D9: n.a. | E9: n.a. | F9: 0.0045 | G9: 13.8 | H9: n.a. | I9: 4/30–6/2/2026
A10: HYG (High Yield) | B10: 0.0643 | C10: 0.0689 | D10: 2.98 | E10: 3.66 | F10: 0.0049 | G10: 16.8 | H10: =C10/D10 -> 0.023120805 | I10: 5/7/2026
A11: MBB (Agency MBS) | B11: 0.042 | C11: 0.0491 | D11: 5.3 | E11: 6.59 | F11: 0.0004 | G11: 39.7 | H11: =C11/D11 -> 0.0092641509 | I11: 6/15/2026
A12: CMBS (CMBS) | B12: 0.0394 | C12: 0.0456 | D12: n.a. | E12: n.a. | F12: 0.0025 | G12: 0.5 | H12: n.a. | I12: 4/17/2026
A14: Note: CMBS effective duration/WAM not published on the fund page at retrieval; historically ~4 yrs. PFF holds perpetual preferreds (no stated maturity).
A15: Yield per Yr of Duration = YTM ÷ effective duration; a simple carry-vs-rate-risk efficiency measure.
