Workbook

Sheet Target Allocation $1M
A1: ACCM Target Portfolio Allocation — $1,000,000 (Inception 6/1/2026)
A2: Working version. Higher-for-longer outlook; slightly aggressive posture. Gold considered and rejected (record price ~$4,110, zero yield vs 3.7% bills, high opportunity cost under strong nominal growth).
A4: Strategic Asset Allocation
A5: Sleeve | B5: Weight | C5: $ Amount | D5: Policy Range | E5: Within Policy?
A6: Equities (11 sector ETFs + JPM, JPM ≤ 5%) | B6: 0.75 | C6: =B6*$C$10 -> 750000 | D6: 60–80% | E6: =IF(AND(B6>=0.6,B6<=0.8),"Yes","NO") -> Yes
A7: Fixed Income | B7: 0.21 | C7: =B7*$C$10 -> 210000 | D7: 20–40% | E7: =IF(AND(B7>=0.2,B7<=0.4),"Yes","NO") -> Yes
A8: Cash & Equivalents (BIL) | B8: 0.04 | C8: =B8*$C$10 -> 40000 | D8: 0–20% | E8: =IF(AND(B8>=0,B8<=0.2),"Yes","NO") -> Yes
A9: Gold ETF — not used | B9: 0 | C9: =B9*$C$10 -> 0 | D9: 0–5% | E9: =IF(AND(B9>=0,B9<=0.05),"Yes","NO") -> Yes
A10: Total | B10: =SUM(B6:B9) -> 1 | C10: 1000000 | D10: Portfolio value ($)
A12: Equity Sleeve Split (foreign = 28% of equity sleeve; policy max 50%)
A13: Segment | B13: % of Equity | C13: $ Amount
A14: U.S. Equities — 11 sector ETFs + JPM (see US Sector Allocation sheet) | B14: 0.72 | C14: =B14*$C$6 -> 540000
A15: International — Emerging Markets: IEMG (MSCI EM: China, India, Korea, Taiwan) | B15: 0.16 | C15: =B15*$C$6 -> 120000
A16: International — Developed Markets: IEFA (MSCI EAFE) | B16: 0.12 | C16: =B16*$C$6 -> 90000
A17: Fixed Income Sleeve — Active for credit/MBS, passive for Treasuries
A18: Holding | B18: Mgmt | C18: % of FI | D18: $ Amount | E18: Yield (SEC/YTW) | F18: Eff. Duration | G18: Expense | H18: AUM ($B)
A19: SPTI — SPDR Interm. Treasury | B19: Passive | C19: 0.35 | D19: =C19*$C$7 -> 73500 | E19: 0.0428 | F19: 4.9 | G19: 0.0003 | H19: 10.3
A20: FBND — Fidelity Total Bond (IG core-plus) | B20: Active | C20: 0.25 | D20: =C20*$C$7 -> 52500 | E20: 0.0461 | F20: 6 | G20: 0.0036 | H20: 26.7
A21: HYG — iShares High Yield | B21: Passive* | C21: 0.2 | D21: =C21*$C$7 -> 42000 | E21: 0.0689 | F21: 3 | G21: 0.0049 | H21: 16.8
A22: JMBS — Janus Active MBS | B22: Active | C22: 0.2 | D22: =C22*$C$7 -> 42000 | E22: 0.049 | F22: 6.21 | G22: 0.0021 | H22: 6.8
A23: FI Sleeve Total / Weighted Avg | C23: =SUM(C19:C22) -> 1 | D23: =SUM(D19:D22) -> 210000 | E23: =SUMPRODUCT(C19:C22,E19:E22) -> 0.050085 | F23: =SUMPRODUCT(C19:C22,F19:F22) -> 5.057 | G23: =SUMPRODUCT(C19:C22,G19:G22) -> 0.002405
A25: vs. Bloomberg U.S. Aggregate benchmark: 4.77% YTM / 4.53% SEC yield, 5.81-yr duration (AGG ETF, ishares.com, 7/1/2026) — sleeve out-yields the benchmark on both bases with ~0.7 yrs less rate risk.
A26: *High yield kept passive: the active alternative (BRHY, iShares High Yield Active) has only ~$99M AUM and a June 2024 inception — fails ACCM AUM and track-record screens. SPTL excluded (14.2-yr duration vs. ACCM 4.9% 10Y forecast); CMBS excluded ($0.5B AUM, 0.29% bid/ask); PFF excluded (0.73 equity correlation, 0.45% fee).
A27: Sources: ssga.com, ishares.com, fidelity.com fund pages, June–July 2026. JMBS: janushenderson.com fund page — eff. duration 6.21, 30-day SEC yield 4.90% (5/31/26), 12-mo distribution yield 5.19% (7/1/26).

Sheet US Sector Allocation
A1: U.S. Equity Sleeve — Sector Allocation vs. Russell 3000 (GICS)
A2: Benchmark: iShares Russell 3000 ETF (IWV) GICS sector weights as of 7/2/2026, ishares.com (screenshot on file); 11 sectors normalized to 100% (excludes 0.79% cash/other).
A4: U.S. Equity Sleeve ($) | B4: ='Target Allocation $1M'!C14 -> 540000
A6: Sector | B6: ETF / Holding | C6: R3000 Wt (7/2/26) | D6: ACCM Wt | E6: Active Bet | F6: $ Amount
A7: Information Technology | B7: XLK | C7: 0.34218498 | D7: 0.36 | E7: =D7-C7 -> 0.017815024 | F7: =D7*$B$4 -> 194400
A8: Financials | B8: XLF + JPM (JPM = $50,000, 5% cap) | C8: 0.12782714 | D8: 0.17 | E8: =D8-C8 -> 0.042172859 | F8: =D8*$B$4 -> 91800
A9: Industrials | B9: XLI | C9: 0.10369548 | D9: 0.125 | E9: =D9-C9 -> 0.021304523 | F9: =D9*$B$4 -> 67500
A10: Health Care | B10: XLV | C10: 0.099454766 | D10: 0.06 | E10: =D10-C10 -> -0.039454766 | F10: =D10*$B$4 -> 32400
A11: Consumer Discretionary | B11: XLY | C11: 0.095516963 | D11: 0.095 | E11: =D11-C11 -> -0.00051696284 | F11: =D11*$B$4 -> 51300
A12: Communication Services | B12: XLC | C12: 0.094810178 | D12: 0.09 | E12: =D12-C12 -> -0.0048101777 | F12: =D12*$B$4 -> 48600
A13: Consumer Staples | B13: XLP | C13: 0.044830372 | D13: 0.02 | E13: =D13-C13 -> -0.024830372 | F13: =D13*$B$4 -> 10800
A14: Energy | B14: XLE | C14: 0.024030695 | D14: 0.045 | E14: =D14-C14 -> 0.020969305 | F14: =D14*$B$4 -> 24300
A15: Real Estate | B15: XLRE | C15: 0.022920032 | D15: 0.01 | E15: =D15-C15 -> -0.012920032 | F15: =D15*$B$4 -> 5400
A16: Materials | B16: XLB | C16: 0.022415186 | D16: 0.015 | E16: =D16-C16 -> -0.0074151858 | F16: =D16*$B$4 -> 8100
A17: Utilities | B17: XLU | C17: 0.022314216 | D17: 0.01 | E17: =D17-C17 -> -0.012314216 | F17: =D17*$B$4 -> 5400
A18: Total | C18: =SUM(C7:C17) -> 1 | D18: =SUM(D7:D17) -> 1 | E18: =SUM(E7:E17) -> -1.994932e-16 | F18: =SUM(F7:F17) -> 540000
A20: Thesis (aggressive posture, sized to conviction): overweights Financials +4.2, Industrials +2.1, Energy +2.1, Info Tech +1.8 all express the higher-for-longer / AI-buildout view; funded by rate-sensitive defensives (Health Care -3.9, Staples -2.5, Real Estate -1.3, Utilities -1.2). All 11 sectors held (diversification policy). Cost acknowledged: higher tracking error vs. benchmark and equity beta modestly above 1 - disclosed and monitored.
A21: JPM is ~55% of the Financials allocation ($50,000 of $91,800) - deliberate single-name conviction from the ACCM equity research report (BUY, $342 target); XLF diversifies the remainder. JPM = 5.0% of total portfolio (policy max).

Sheet Model Linkage
A1: Model Linkage — Economic Model to Capital Markets Outlook
A2: Shows how each expected-return input comes from the ACCM Economic and Inflation Model (frozen July 31, 2026).
A3: The US equity earnings-growth input is built here. The Expected Returns CMO sheet points at it.
A6: U.S. equity earnings growth — build
A7: Component | B7: Value | C7: Source / derivation
A8: Nominal GDP growth | B8: 0.052429 | C8: ACCM Economic and Inflation Model, SUMMARY sheet (frozen July 31, 2026)
A9: AI-driven margin contribution | B9: 0.025 | C9: ASSUMPTION: operating leverage from the data-center buildout accruing to index constituents
A10: U.S. EQUITY EARNINGS GROWTH | B10: =B8+B9 -> 0.077429 | C10: Carried to Expected Returns CMO cell C5
A21: The finding. Expected active return is insensitive to the level of the US equity forecast. US equities are 54% of the
A22: portfolio against 50% of the benchmark, so a change in their expected return shifts both sides by almost the same amount.
A23: Active return comes from the tilts - emerging markets over developed, the fixed income sleeve over the aggregate index -
A24: not from the level of the equity forecast.
A26: Optimizer note. The scenario weights on the Optimizer sheet were solved in Excel Solver under the policy constraints. Lowering the US equity
A27: expected return from 7.10% to 6.52% widens the gap to emerging markets, so it would push an unconstrained solution further toward EM.
A28: Max Return and Max Sharpe already sit at their constraint bounds (40% US equity, 40% EM), so those are unchanged. Re-run Solver before
A29: relying on the interior Min StdDev solution.

Sheet Port Comparisons
A1: Benchmark Returns | E1: ACCM Returns
A2: Description | B2: Date | C2: Return | E2: Description | G2: Return
A3: Russell 3000 ETF (VTHR US) | B3: 46174 | C3: 332.91595 | E3: Domestic Equities | H3: Fixed Income
A4: Last Updated | B4: 46203 | C4: 331.42999 | E4: DEQ | F4: Cost | G4: 540000 | H4: FI | I4: Cost | J4: 210000
A5: Return | C5: =C4/C3-1 -> -0.0044634746 | E5: DEQ | F5: Market Value | G5: 545189.9 | H5: FI | I5: Market Value | J5: 210642.33
E6: Return | G6: =IFERROR((G5)/G4-1,0) -> 0.0096109259 | H6: Return | J6: =(J5)/J4-1 -> 0.0030587143
A7: MSCI ACWI ex-US ETF (ACWX US) | B7: 46174 | C7: 76.082657
A8: Last Updated: | B8: 46203 | C8: 76.110001 | E8: International Equities | H8: Cash
A9: Return | C9: =C8/C7-1 -> 0.00035939531 | E9: EMEQ | F9: Cost | G9: 120000 | H9: Cash | J9: 0
A10: Total Equity | C10: =(5/7*C5+2/7*C9) -> -0.0030855118 | E10: EMEQ | F10: Market Value | G10: 117640.93
E11: Return | G11: =IFERROR(G10/G9-1,0) -> -0.019658917 | H11: Cash (BIL) | I11: Cost | J11: 40000
A12: US Aggregate Bond ETF (AGG US) | B12: 46174 | C12: 98.350006 | I12: Market Value | J12: 40105.03
A13: Last Updated: | B13: 46203 | C13: 98.649002 | E13: DMEQ | F13: Cost | G13: 90000 | J13: =J12/J11-1 -> 0.00262575
A14: Return | C14: =C13/C12-1 -> 0.0030401215 | E14: DMEQ | F14: Market Value | G14: 90489.58
E15: Return | G15: =IFERROR(G14/G13-1,0) -> 0.0054397778 | H15: Total Portfolio Cost | J15: =G4+G9+G13+J4+J11 -> 1000000
A16: Benchmark Return (R3000 50% / MSCI ex. U.S. 20% / AGG 30%) | C16: =(C5*0.5)+(C9*0.2)+(C14*0.3) -> -0.0012478218 | E16: Total International Return | G16: =(G10+G14)/(G9+G13)-1 -> -0.0089023333 | H16: Total Portfolio Value | J16: =G5+G10+G14+J5+J9+J12 -> 1004067.8
E17: Total Equity Return | G17: =(G5+G10+G14)/(G4+G9+G13)-1 -> 0.0044272133 | H17: Angel City Capital Management Return | J17: =J16/J15-1 -> 0.00406777
H18: Relative Performance | J18: =J17-C16 -> 0.0053155918
A20: June 2026 one-month backtest (6/1–6/30 closes, dividend-adjusted). Values: yfinance total-return data; verified against Bloomberg PORT (portfolio +0.401%, benchmark −0.130%, active +0.531%).

Sheet Screener Criteria
A1: ACCM Equity Screener — Bloomberg EQS (growth at a reasonable price, adapted to higher-for-longer outlook)
A2: Two-stage process. STAGE 1 (EQS, as run): universe 1,650,965 -> active 605,134 -> US exchanges 29,256 -> US domicile 15,663 -> GICS Financials 1,044 -> mkt cap >= $20B: 76 -> latest quarterly revenue growth YoY > 0: 65 -> ROE > 10%: 50 names. STAGE 2 (evaluation of output): rows below; bank variant applies since sector = Financials. JPM selected: largest bank, highest bank ROE (17.0%), growth within 0.4pt of bank leader.
A4: # | B4: Criterion | C4: Direction / Threshold | D4: Rationale (link to outlook)
A5: 1 | B5: Country of domicile: United States | C5: Equals: US | D5: Policy universe (NYSE/AMEX/NASDAQ); U.S.-centric outlook
A6: 2 | B6: GICS Sector | C6: Equals: [input sector] | D6: Screen run within the sector being allocated
A7: 3 | B7: Market capitalization | C7: >= $20B | D7: Liquidity / "easily marketable" per investment policy
A8: 4 | B8: Revenue growth, FY2021-FY2025 | C8: Higher better (rank) | D8: Growth tilt: 10-yr style analysis shows Pure Growth Sharpe 0.66 vs Value 0.42
A9: 5 | B9: Revenue growth, FY2026E-FY2028E (consensus) | C9: Higher better (rank) | D9: Forward growth consistent with 5.4% nominal GDP outlook
A10: 6 | B10: Diluted EPS growth, FY2021-FY2025 | C10: Higher better (rank) | D10: Profitable growth, not just top line
A11: 7 | B11: EPS growth, FY2026E-FY2028E (consensus) | C11: Higher better (rank) | D11: Earnings momentum into the forecast window
A12: 8 | B12: PEG ratio (fwd P/E / fwd EPS growth) | C12: <= ~2.0; lower better | D12: Valuation guard: elevated rates cap multiple expansion - pay for growth, not hype
A13: 9 | B13: Price / Free Cash Flow | C13: Lower better (rank) | D13: Professor-specified: growth companies that are relatively cheaper
A14: 10 | B14: ROIC | C14: Higher better (rank) | D14: Quality: returns above cost of capital when capital is no longer cheap
A15: 11 | B15: EBIT / Interest expense | C15: >= 5x | D15: Higher-for-longer: refinancing at ~4.9% 10Y punishes weak balance sheets
A17: Financials variant (bank metrics; cash-flow ratios are not meaningful for banks):
A18: 9b | B18: Return on Equity | C18: Higher better; >= 12% | D18: Bank profitability metric; JPM ~17% vs peers
A19: 10b | B19: Price/Book vs. ROE | C19: P/B justified by ROE spread over Ke | D19: Consistent with DGM valuation framework
A20: 11b | B20: Dividend + buyback growth | C20: Higher better | D20: Feeds the DGM: value = capitalized cash to shareholders
A21: 12b | B21: CET1 / Tier 1 capital | C21: Above regulatory minimum + buffer | D21: Balance-sheet strength; stress-test resilience
A23: Outcome: within Financials, the screen surfaced large-cap banks with superior ROE and EPS growth; JPMorgan Chase selected on combined screen rank + DGM upside (see Equity Research Report, BUY, $342 target).

Sheet Sector ETF Selection
A1: Sector ETF Family Comparison — Fund Selection Criteria (Guidelines Section F)
A3: Criterion | B3: Select Sector SPDRs (XL…) — CHOSEN | C3: Vanguard Sector ETFs | D3: Fidelity MSCI Sector ETFs | E3: iShares U.S. Sector ETFs
A4: Expense ratio | B4: 0.08% (all 11 funds) | C4: ~0.09–0.10% | D4: ~0.084% | E4: ~0.39–0.40%
A5: AUM range | B5: $8B–$125B (largest) | C5: $5B–$90B | D5: $1B–$10B | E5: $0.5B–$5B
A6: Liquidity / spreads | B6: Deepest volume, ~1bp spreads | C6: Good | D6: Moderate | E6: Moderate
A7: Index / coverage | B7: S&P 500 sectors (large-cap), GICS | C7: MSCI 25/50 broad (incl. mid/small) | D7: MSCI 25/50 broad | E7: Russell/S&P mixes
A8: Benchmark fit vs R3000 | B8: Large-cap only (~90%+ of R3000 wt) | C8: Closest to R3000 coverage | D8: Close | E8: Varies
A9: Inception | B9: 1998 (longest live record) | C9: 2004 | D9: 2013 | E9: 2000
A10: Methodological consistency | B10: Single family, uniform GICS, all 11 sectors | C10: Uniform | D10: Uniform | E10: Uniform
A12: Decision: Select Sector SPDR suite chosen on expense (0.08%), AUM/liquidity (largest and most traded sector ETFs), longest live track record, and methodological consistency (one index family, GICS definitions matching our sector framework).
A13: Acknowledged trade-off: XL funds hold S&P 500 constituents only; Vanguard sector funds cover more of the Russell 3000 small/mid tail but at higher cost and lower liquidity. Non-XL figures approximate — verify current values if cited directly.

Sheet Expected Returns CMO
A1: Capital Markets Outlook — 12-Month Expected Returns by Asset Class (building-block method)
A2: Blue inputs tie to the ACCM Economic and Inflation Model, frozen July 31, 2026: nominal GDP 5.24%, inflation 3.43%, ten-year Treasury 4.90%. The US equity earnings-growth input is built on the Model Linkage sheet.
A4: Asset Class | B4: Income / Yield | C4: Growth / Roll | D4: Valuation / Rate Impact | E4: Expected Return | F4: Rationale
A5: U.S. Equities (Russell 3000) | B5: 0.011 | C5: ='Model Linkage'!B10 -> 0.077429 | D5: -0.025 | E5: =B5+C5+D5 -> 0.063429 | F5: Dividend yield 1.1% (FTSE factsheet 5/31/26) plus buyback ~1%. Earnings growth 7.74% = nominal GDP 5.24% + 2.5pt AI margin contribution. Less 2.5pt multiple compression as the ten-year drifts toward 4.90%.
A6: Intl Developed (MSCI EAFE) | B6: 0.03 | C6: 0.04 | D6: -0.02 | E6: =B6+C6+D6 -> 0.05 | F6: Higher div yield; weak EU/Japan growth per ACCM outlooks; modest de-rating risk
A7: Emerging Markets (MSCI EM) | B7: 0.025 | C7: 0.08 | D7: -0.02 | E7: =B7+C7+D7 -> 0.085 | F7: India consumption, China tech, Korea/Taiwan AI supply chain; earnings ~8%; EM multiples already re-rated after 2025-26 rally
A8: U.S. Aggregate Bonds | B8: 0.046 | C8: 0 | D8: -0.018 | E8: =B8+C8+D8 -> 0.028 | F8: YTW ~4.6%; duration ~6.0 x +30bp belly rise as 10Y drifts toward 4.9% forecast
A9: ACCM FI Sleeve | B9: 0.05 | C9: 0 | D9: -0.015 | E9: =B9+C9+D9 -> 0.035 | F9: Sleeve blended yield (mix of YTM, YTW and SEC yield; see Target Allocation) 5.01%, duration 5.06 (see Target Allocation); same +30bp rate drift
A10: Cash (1-3mo T-Bills) | B10: 0.037 | C10: 0 | D10: 0 | E10: =B10+C10+D10 -> 0.037 | F10: Current bill yield 3.7%; Fed on hold (hike risk = upside to this figure)
A13: Portfolio Return Goal vs. Benchmark Expected Return
A14: ACCM Portfolio (75% eq: 54% US / 12% EM / 9% DM; 21% FI sleeve; 4% cash) | E14: =0.54*E5+0.12*E7+0.09*E6+0.21*E9+0.04*E10 -> 0.05778166
A15: Blended Benchmark (50% R3000 / 20% ACWI ex-US ≈ 75% DM + 25% EM / 30% Agg) | E15: =0.5*E5+0.2*(0.75*E6+0.25*E7)+0.3*E8 -> 0.0518645
A16: Expected active return (allocation tilts, before JPM security selection) | E16: =E14-E15 -> 0.00591716
A18: JPM contribution: the DGM implies a 16.1% twelve-month total return against 6.3% for US equities on the same basis. At a 5% portfolio weight that adds about 0.49 points to the portfolio expected return through security selection.
A19: Risk context: optimizer covariance (10-yr monthly) puts portfolio std dev near ~11%; expected Sharpe ≈ (ER − cash) / σ. One-year expectations are planning inputs, not forecasts of realized returns.

Sheet Optimizer (Expected)
A1: Optimizer Rerun — ACCM Expected Returns, Historical Covariance (HW4 method, June 23 class)
A2: Expected returns from Expected Returns CMO sheet; covariance matrix = 10-yr monthly (N=120) from HW4 optimizer. Constraints: equity 60-80%, FI 20-40%, cash 0-20%, foreign <= 50% of equity. Optimization solved numerically; weights below are the solved values, metrics computed live.
A4: Asset | B4: Annual ER | C4: Monthly mu
A5: US Equity (R3000) | B5: ='Expected Returns CMO'!E5 -> 0.063429 | C5: =(1+B5)^(1/12)-1 -> 0.0051380374
A6: Intl Developed (M1EA) | B6: ='Expected Returns CMO'!E6 -> 0.05 | C6: =(1+B6)^(1/12)-1 -> 0.0040741238
A7: Emerging Mkts (M1EF) | B7: ='Expected Returns CMO'!E7 -> 0.085 | C7: =(1+B7)^(1/12)-1 -> 0.0068214934
A8: Bonds (Agg) | B8: ='Expected Returns CMO'!E8 -> 0.028 | C8: =(1+B8)^(1/12)-1 -> 0.0023039139
A9: Cash (T-Bills) | B9: ='Expected Returns CMO'!E10 -> 0.037 | C9: =(1+B9)^(1/12)-1 -> 0.0030322488
A11: Monthly Variance-Covariance Matrix (source: Portfolio Optimizer HW4, 10-yr monthly)
B12: US Equity (R3000) | C12: Intl Developed (M1EA) | D12: Emerging Mkts (M1EF) | E12: Bonds (Agg) | F12: Cash (T-Bills)
A13: US Equity (R3000) | B13: 0.0020644783 | C13: 0.0016416002 | D13: 0.0015581278 | E13: 0.0002635516 | F13: 7.158425e-07
A14: Intl Developed (M1EA) | B14: 0.0016416002 | C14: 0.0018851713 | D14: 0.0017314099 | E14: 0.0003004403 | F14: 3.476718e-06
A15: Emerging Mkts (M1EF) | B15: 0.0015581278 | C15: 0.0017314099 | D15: 0.0025175795 | E15: 0.0003145125 | F15: 3.163929e-06
A16: Bonds (Agg) | B16: 0.0002635516 | C16: 0.0003004403 | D16: 0.0003145125 | E16: 0.0002134413 | F16: 3.462105e-06
A17: Cash (T-Bills) | B17: 7.158425e-07 | C17: 3.476718e-06 | D17: 3.163929e-06 | E17: 3.462105e-06 | F17: 2.579867e-06
A19: Scenario Weights & Metrics
A20: Asset | C20: Max Return | D20: Min StdDev | E20: Max Sharpe | F20: ACCM chosen | G20: Benchmark 50/20/30
A21: US Equity (R3000) | C21: 0.4 | D21: 0.301 | E21: 0.4001 | F21: 0.54 | G21: 0.5
A22: Intl Developed (M1EA) | C22: 0 | D22: 0.2062 | E22: 0 | F22: 0.09 | G22: 0.15
A23: Emerging Mkts (M1EF) | C23: 0.4 | D23: 0.0928 | E23: 0.3999 | F23: 0.12 | G23: 0.05
A24: Bonds (Agg) | C24: 0.2 | D24: 0.2 | E24: 0.2 | F24: 0.21 | G24: 0.3
A25: Cash (T-Bills) | C25: 0 | D25: 0.2 | E25: 0 | F25: 0.04 | G25: 0
A26: Sum of weights | C26: =SUM(C21:C25) -> 1 | D26: =SUM(D21:D25) -> 1 | E26: =SUM(E21:E25) -> 1 | F26: =SUM(F21:F25) -> 1 | G26: =SUM(G21:G25) -> 1
A28: Helper: (Cov x w) per asset
A29: US Equity (R3000) | C29: {=MMULT($B13:$F13,C$21:C$25)} -> 0.0015017528 | D29: {=MMULT($B13:$F13,D$21:D$25)} -> 0.0011573537 | E29: {=MMULT($B13:$F13,E$21:E$25)} -> 0.0015018034 | F29: {=MMULT($B13:$F13,F$21:F$25)} -> 0.0015049121 | G29: {=MMULT($B13:$F13,G$21:G$25)} -> 0.001435451
A30: Intl Developed (M1EA) | C30: {=MMULT($B14:$F14,C$21:C$25)} -> 0.0014092921 | D30: {=MMULT($B14:$F14,D$21:D$25)} -> 0.0011043022 | E30: {=MMULT($B14:$F14,E$21:E$25)} -> 0.0014092831 | F30: {=MMULT($B14:$F14,F$21:F$25)} -> 0.0013271302 | G30: {=MMULT($B14:$F14,G$21:G$25)} -> 0.0012802784
A31: Emerging Mkts (M1EF) | C31: {=MMULT($B15:$F15,C$21:C$25)} -> 0.0016931854 | D31: {=MMULT($B15:$F15,D$21:D$25)} -> 0.0011231799 | E31: {=MMULT($B15:$F15,E$21:E$25)} -> 0.0016930895 | F31: {=MMULT($B15:$F15,F$21:F$25)} -> 0.0013654996 | G31: {=MMULT($B15:$F15,G$21:G$25)} -> 0.0012590081
A32: Bonds (Agg) | C32: {=MMULT($B16:$F16,C$21:C$25)} -> 0.0002739139 | D32: {=MMULT($B16:$F16,D$21:D$25)} -> 0.00021384726 | E32: {=MMULT($B16:$F16,E$21:E$25)} -> 0.0002739088 | F32: {=MMULT($B16:$F16,F$21:F$25)} -> 0.00025206015 | G32: {=MMULT($B16:$F16,G$21:G$25)} -> 0.00025659986
A33: Cash (T-Bills) | C33: {=MMULT($B17:$F17,C$21:C$25)} -> 2.2443296e-06 | D33: {=MMULT($B17:$F17,D$21:D$25)} -> 2.4343749e-06 | E33: {=MMULT($B17:$F17,E$21:E$25)} -> 2.2440848e-06 | F33: {=MMULT($B17:$F17,F$21:F$25)} -> 1.9093678e-06 | G33: {=MMULT($B17:$F17,G$21:G$25)} -> 2.0762569e-06
A35: Monthly return | C35: =SUMPRODUCT($C$5:$C$9,C21:C25) -> 0.0052445951 | D35: =SUMPRODUCT($C$5:$C$9,D21:D25) -> 0.0040869007 | E35: =SUMPRODUCT($C$5:$C$9,E21:E25) -> 0.0052444267 | F35: =SUMPRODUCT($C$5:$C$9,F21:F25) -> 0.0045649024 | G35: =SUMPRODUCT($C$5:$C$9,G21:G25) -> 0.0042123861
A36: Annual return | C36: =(1+C35)^12-1 -> 0.064782636 | D36: =(1+D35)^12-1 -> 0.050160347 | E36: =(1+E35)^12-1 -> 0.064780497 | F36: =(1+F35)^12-1 -> 0.056175303 | G36: =(1+G35)^12-1 -> 0.051736351
A37: Annual std dev | C37: =SQRT(SUMPRODUCT(C21:C25,C29:C33)*12) -> 0.12646382 | D37: =SQRT(SUMPRODUCT(D21:D25,D29:D33)*12) -> 0.093180985 | E37: =SQRT(SUMPRODUCT(E21:E25,E29:E33)*12) -> 0.126462 | F37: =SQRT(SUMPRODUCT(F21:F25,F29:F33)*12) -> 0.11742044 | G37: =SQRT(SUMPRODUCT(G21:G25,G29:G33)*12) -> 0.11223356
A38: Sharpe (vs cash ER) | C38: =(C36-$B$9)/C37 -> 0.21968842 | D38: =(D36-$B$9)/D37 -> 0.14123426 | E38: =(E36-$B$9)/E37 -> 0.21967466 | F38: =(F36-$B$9)/F37 -> 0.16330465 | G38: =(G36-$B$9)/G37 -> 0.13130075
A41: Interpretation: with ACCM expected returns, Max Sharpe and Max Return converge on the same corner solution - 40% US / 40% EM equity - because EM carries the
A42: highest expected return and the foreign limit (50% of equity) binds. ACCM tempers this to 12% EM (still ~2.4x the benchmark weight): a 40% single-region EM
A43: position ignores estimation error in expected returns, single-region concentration risk, and EM volatility (17.5% ann.). The chosen 75/21/4 portfolio earns a
A44: higher expected return AND higher Sharpe than the benchmark, sitting deliberately between Min StdDev and Max Sharpe. The Min StdDev
A45: weights are a numerical solution and are approximate. An independent solve gives a volatility within half a basis point.
